andromeda/__init__.py
andromeda/inference.py
andromeda_api-0.1.7.dist-info/METADATA
andromeda_api-0.1.7.dist-info/WHEEL
andromeda_api-0.1.7.dist-info/top_level.txt
andromeda_api-0.1.7.dist-info/RECORD
