Metadata-Version: 2.4
Name: andromeda-api
Version: 0.1.7
Summary: Andromeda API Inference Client by Prosilico AB
Author-email: Morgan Ekmefjord <morgan@prosilico.com>
License: MIT
Project-URL: Homepage, https://www.prosilico.com
Requires-Python: >=3.7
Requires-Dist: requests
Requires-Dist: python-dotenv
